postscriptum/__about__.py
postscriptum/__init__.py
postscriptum/excepthook.py
postscriptum/exceptions.py
postscriptum/pubsub.py
postscriptum/signals.py
postscriptum/system_exit.py
postscriptum/types.py
postscriptum/utils.py
postscriptum-0.3.dist-info/LICENCE
postscriptum-0.3.dist-info/METADATA
postscriptum-0.3.dist-info/WHEEL
postscriptum-0.3.dist-info/top_level.txt
postscriptum-0.3.dist-info/RECORD
