Metadata-Version: 2.1
Name: postscriptum
Version: 0.3
Summary: An unified API to run code when Python exits
Home-page: https://github.com/ksamuel/postscriptum/
Author: Bite Code
Author-email: contact@bitecode.dev
License: MIT
Keywords: atexit,excepthook,signals
Platform: UNKNOWN
Classifier: License :: OSI Approved :: MIT License
Classifier: Programming Language :: Python :: 3 :: Only
Classifier: Programming Language :: Python :: 3.6
Classifier: Programming Language :: Python :: 3.7
Classifier: Programming Language :: Python :: 3.8
Requires-Dist: ordered-set (<4,>=3.1.1)
Requires-Dist: ordered-set-stubs (>=0.1.3)
Requires-Dist: typing-extensions (<4,>=3.7)
